optimitz/__init__.py
optimitz/search.py
optimitz/solution.py
optimitz-0.0.2.dist-info/METADATA
optimitz-0.0.2.dist-info/WHEEL
optimitz-0.0.2.dist-info/licenses/LICENSE
optimitz-0.0.2.dist-info/RECORD
