Metadata-Version: 2.4
Name: optimitz
Version: 0.0.2
Summary: Evolutionary algorithms for optimization problems
Project-URL: Homepage, https://github.com/artitzco/optimitz
Project-URL: Issues, https://github.com/artitzco/optimitz/issues
Author-email: Artitzco <artitzco@proton.me>
License-File: LICENSE
Classifier: License :: OSI Approved :: GNU General Public License v3 (GPLv3)
Classifier: Operating System :: OS Independent
Classifier: Programming Language :: Python :: 3
Requires-Python: >=3.0
Requires-Dist: bitarray
Requires-Dist: numpy
Requires-Dist: pandas
Requires-Dist: scipy
